eb_prune/__init__.py
eb_prune-0.4.3.dist-info/LICENSE.txt
eb_prune-0.4.3.dist-info/METADATA
eb_prune-0.4.3.dist-info/WHEEL
eb_prune-0.4.3.dist-info/entry_points.txt
eb_prune-0.4.3.dist-info/top_level.txt
eb_prune-0.4.3.dist-info/RECORD
