Metadata-Version: 2.1
Name: eb-prune
Version: 0.4.3
Summary: Pruning of Elastic Beanstalk versions.
Home-page: https://www.shore.co.il/git/eb-prune
Author: Nimrod Adar
Author-email: nimrod@shore.co.il
License: License :: OSI Approved :: MIT License
Keywords: beanstalk AWS
Platform: UNKNOWN
Classifier: Development Status :: 4 - Beta
Classifier: Intended Audience :: Developers
Classifier: Programming Language :: Python :: 3
Classifier: Programming Language :: Python :: 3.6
Classifier: Programming Language :: Python :: 3.7
Classifier: Programming Language :: Python :: 3.8
Classifier: Programming Language :: Python :: 3.9
Classifier: Programming Language :: Python :: 2
Classifier: Intended Audience :: System Administrators
Classifier: Topic :: Utilities
Requires-Dist: botocore
Provides-Extra: dev
Requires-Dist: pre-commit ; extra == 'dev'
Requires-Dist: twine ; extra == 'dev'
